Workbook

Sheet Inputs
A1: Parameter | B1: Value | C1: Notes
A2: Learners per Year | B2: 1000 | C2: Number of Shortcut learners
A3: Shortcut Ticket (INR) | B3: 200000 | C3: Avg certification fee
A4: Shortcut Margin % | B4: 0.4 | C4: Gross margin
A5: LevelUpMax Ticket (INR) | B5: 400000 | C5: Outcome assurance fee
A6: LevelUpMax Margin % | B6: 0.4 | C6: Gross margin
A7: Frankmax GCC Value per Employee (INR) | B7: 1000000 | C7: Avg enterprise value generated
A8: Frankmax Margin % | B8: 0.3 | C8: Consulting margin
A9: Aureya Royalty per Learner (INR) | B9: 50000 | C9: IP/Data royalty estimate

Sheet Shortcut
A1: Metric | B1: Formula / Value
A2: Learners | B2: =Inputs!B2
A3: Ticket Price | B3: =Inputs!B3
A4: Revenue | B4: =B2*B3
A5: Margin % | B5: =Inputs!B4
A6: Profit | B6: =B4*B5

Sheet LevelUpMax
A1: Metric | B1: Formula / Value
A2: Learners | B2: =Inputs!B2
A3: Ticket Price | B3: =Inputs!B5
A4: Revenue | B4: =B2*B3
A5: Margin % | B5: =Inputs!B6
A6: Profit | B6: =B4*B5

Sheet Frankmax
A1: Metric | B1: Formula / Value
A2: Learners deployed | B2: =Inputs!B2
A3: Enterprise Value per Employee | B3: =Inputs!B7
A4: Revenue | B4: =B2*B3
A5: Margin % | B5: =Inputs!B8
A6: Profit | B6: =B4*B5

Sheet Aureya_Bridge
A1: Metric | B1: Formula / Value
A2: Shortcut Revenue | B2: =Shortcut!B4
A3: LevelUpMax Revenue | B3: =LevelUpMax!B4
A4: Frankmax Revenue | B4: =Frankmax!B4
A5: Aureya Royalty | B5: =Inputs!B2*Inputs!B9
A6: Total Ecosystem Revenue | B6: =SUM(B2:B5)
A7: Shortcut Profit | B7: =Shortcut!B6
A8: LevelUpMax Profit | B8: =LevelUpMax!B6
A9: Frankmax Profit | B9: =Frankmax!B6
A10: Total Ecosystem Profit | B10: =SUM(B7:B9)

Sheet Dashboard
A1: AUREYA ECOSYSTEM DASHBOARD
A2: Total Learners | B2: =Inputs!B2
A3: Total Ecosystem Revenue | B3: =Aureya_Bridge!B6
A4: Total Ecosystem Profit | B4: =Aureya_Bridge!B10
A5: Shortcut Revenue | B5: =Shortcut!B4
A6: LevelUpMax Revenue | B6: =LevelUpMax!B4
A7: Frankmax Revenue | B7: =Frankmax!B4
